azure_keyvault_browser/__init__.py
azure_keyvault_browser/app.py
azure_keyvault_browser/ask.py
azure_keyvault_browser/azure.py
azure_keyvault_browser/config.py
azure_keyvault_browser/renderables/__init__.py
azure_keyvault_browser/renderables/help.py
azure_keyvault_browser/renderables/paginated_table.py
azure_keyvault_browser/renderables/secret_properties.py
azure_keyvault_browser/renderables/secret_versions_table.py
azure_keyvault_browser/renderables/secrets_table.py
azure_keyvault_browser/search.py
azure_keyvault_browser/styles.py
azure_keyvault_browser/util.py
azure_keyvault_browser/widgets/__init__.py
azure_keyvault_browser/widgets/filter.py
azure_keyvault_browser/widgets/flash.py
azure_keyvault_browser/widgets/header.py
azure_keyvault_browser/widgets/help.py
azure_keyvault_browser/widgets/secret_properties.py
azure_keyvault_browser/widgets/secret_versions.py
azure_keyvault_browser/widgets/secrets.py
azure_keyvault_browser-0.0.3.dist-info/entry_points.txt
azure_keyvault_browser-0.0.3.dist-info/LICENSE
azure_keyvault_browser-0.0.3.dist-info/WHEEL
azure_keyvault_browser-0.0.3.dist-info/METADATA
azure_keyvault_browser-0.0.3.dist-info/RECORD
