Metadata-Version: 2.1
Name: azure-keyvault-browser
Version: 0.0.3
Summary: A tool for browsing and searching for secrets in Azure Key Vault
License: MIT
Author: Craig Gumbley
Author-email: craiggumbley@gmail.com
Requires-Python: >=3.7,<4.0
Classifier: License :: OSI Approved :: MIT License
Classifier: Programming Language :: Python :: 3
Classifier: Programming Language :: Python :: 3.10
Classifier: Programming Language :: Python :: 3.7
Classifier: Programming Language :: Python :: 3.8
Classifier: Programming Language :: Python :: 3.9
Requires-Dist: Whoosh (>=2.7.4,<3.0.0)
Requires-Dist: aiohttp (>=3.8.1,<4.0.0)
Requires-Dist: azure-identity (>=1.7.1,<2.0.0)
Requires-Dist: azure-keyvault-secrets (>=4.3.0,<5.0.0)
Requires-Dist: click (>=8.0.3,<9.0.0)
Requires-Dist: rich (>=10.11.0,<11.0.0)
Requires-Dist: textual (==0.1.13)
Requires-Dist: textual-inputs (>=0.2.0,<0.3.0)
Requires-Dist: toml (>=0.10.2,<0.11.0)
Requires-Dist: validators (>=0.18.2,<0.19.0)
